README.md
setup.py
bin/gregory_online
gregory_online/__init__.py
gregory_online/ascgeneric.py
gregory_online/config.py
gregory_online/decay_db.py
gregory_online/dpp2jpg.py
gregory_online/erlang.py
gregory_online/fetchnp.py
gregory_online/histo_analyze.py
gregory_online/histo_displ.py
gregory_online/histo_global_cont.py
gregory_online/histo_io.py
gregory_online/histo_np_ops.py
gregory_online/key_enter.py
gregory_online/topbar.py
gregory_online/utilone.py
gregory_online/utils.py
gregory_online/version.py
gregory_online.egg-info/PKG-INFO
gregory_online.egg-info/SOURCES.txt
gregory_online.egg-info/dependency_links.txt
gregory_online.egg-info/requires.txt
gregory_online.egg-info/top_level.txt
gregory_online/data/Am241.svg
gregory_online/data/Cm247.png
gregory_online/data/Np237.svg
gregory_online/data/Pa231.svg
gregory_online/data/Pu239.svg
gregory_online/data/Th232.svg
gregory_online/data/U235.svg
gregory_online/data/U238.svg
gregory_online/data/decay_lara.parquet
gregory_online/data/testrebin.py