Metadata-Version: 2.1
Name: gregory-online
Version: 0.3.6
Summary: Online watching HTTP server of ROOT on port 9009
Author: me
Author-email: jaromrax@gmail.com
License: GPL2
